[{"id":1,"name":"Standard","price":"$39.85",
"about":"Ut labore et dolore magna aliqua","adults":21,
"image":"image1.jpg"
,"chidrens":1,"rooms":19},
{"id":2,"name":"Suite","price":"$67.85","about":"Consectetur adipiscing elit","adults":8,"image":"image3.jpg","chidrens":2,"rooms":10},
{"id":3,"name":"Standard","price":"$47.29","about":"Ut enim ad minim veniam","adults":7,"image":"image5.jpg","chidrens":3,"rooms":27},
{"id":4,"name":"Suite","price":"$53.97","about":"Consectetur adipiscing elit","adults":20,"image":"image1.jpg","chidrens":4,"rooms":24},
{"id":5,"name":"Deluxe","price":"$18.15","about":"Ut enim ad minim veniam","adults":17,"image":"image2.jpg","chidrens":5,"rooms":25},
{"id":6,"name":"Deluxe","price":"$0.92","about":"Lorem ipsum dolor sit amet","adults":15,"image":"image5.jpg","chidrens":6,"rooms":10},
{"id":7,"name":"Presidential","price":"$64.22","about":"Ut labore et dolore magna aliqua","adults":29,"image":"image2.jpg","chidrens":7,"rooms":29},
{"id":8,"name":"Executive","price":"$60.37","about":"Ut enim ad minim veniam","adults":24,"image":"image3.jpg","chidrens":8,"rooms":2},
{"id":9,"name":"Deluxe","price":"$37.46","about":"Sed do eiusmod tempor incididunt","adults":21,"image":"image5.jpg","chidrens":9,"rooms":12},
{"id":10,"name":"Presidential","price":"$70.06","about":"Ut enim ad minim veniam","adults":21,"image":"image2.jpg","chidrens":10,"rooms":29},
{"id":11,"name":"Executive","price":"$52.67","about":"Ut enim ad minim veniam","adults":4,"image":"image2.jpg","chidrens":11,"rooms":17},
{"id":12,"name":"Executive","price":"$99.16","about":"Lorem ipsum dolor sit amet","adults":23,"image":"image5.jpg","chidrens":12,"rooms":2},
{"id":13,"name":"Executive","price":"$67.31","about":"Consectetur adipiscing elit","adults":13,"image":"image5.jpg","chidrens":13,"rooms":21},
{"id":14,"name":"Suite","price":"$54.40","about":"Ut labore et dolore magna aliqua","adults":28,"image":"image5.jpg","chidrens":14,"rooms":21},
{"id":15,"name":"Suite","price":"$24.69","about":"Sed do eiusmod tempor incididunt","adults":6,"image":"image3.jpg","chidrens":15,"rooms":30},
{"id":16,"name":"Deluxe","price":"$93.41","about":"Consectetur adipiscing elit","adults":28,"image":"image4.jpg","chidrens":16,"rooms":4},
{"id":17,"name":"Presidential","price":"$51.41","about":"Ut enim ad minim veniam","adults":3,"image":"image1.jpg","chidrens":17,"rooms":25},
{"id":18,"name":"Suite","price":"$51.79","about":"Sed do eiusmod tempor incididunt","adults":19,"image":"image1.jpg","chidrens":18,"rooms":2},
{"id":19,"name":"Presidential","price":"$25.57","about":"Ut enim ad minim veniam","adults":14,"image":"image3.jpg","chidrens":19,"rooms":13},
{"id":20,"name":"Presidential","price":"$94.45","about":"Ut labore et dolore magna aliqua","adults":14,"image":"image1.jpg","chidrens":20,"rooms":12},
{"id":21,"name":"Deluxe","price":"$35.97","about":"Sed do eiusmod tempor incididunt","adults":29,"image":"image3.jpg","chidrens":21,"rooms":13},
{"id":22,"name":"Presidential","price":"$34.23","about":"Sed do eiusmod tempor incididunt","adults":14,"image":"image4.jpg","chidrens":22,"rooms":26},
{"id":23,"name":"Executive","price":"$4.83","about":"Lorem ipsum dolor sit amet","adults":6,"image":"image4.jpg","chidrens":23,"rooms":21},
{"id":24,"name":"Executive","price":"$12.33","about":"Lorem ipsum dolor sit amet","adults":22,"image":"image2.jpg","chidrens":24,"rooms":7},
{"id":25,"name":"Executive","price":"$70.37","about":"Consectetur adipiscing elit","adults":29,"image":"image1.jpg","chidrens":25,"rooms":14},
{"id":26,"name":"Presidential","price":"$98.07","about":"Sed do eiusmod tempor incididunt","adults":1,"image":"image4.jpg","chidrens":26,"rooms":28},
{"id":27,"name":"Suite","price":"$45.13","about":"Consectetur adipiscing elit","adults":4,"image":"image1.jpg","chidrens":27,"rooms":4},
{"id":28,"name":"Deluxe","price":"$44.59","about":"Sed do eiusmod tempor incididunt","adults":17,"image":"image4.jpg","chidrens":28,"rooms":14},
{"id":29,"name":"Standard","price":"$68.70","about":"Lorem ipsum dolor sit amet","adults":21,"image":"image2.jpg","chidrens":29,"rooms":13},
{"id":30,"name":"Executive","price":"$13.89","about":"Consectetur adipiscing elit","adults":3,"image":"image3.jpg","chidrens":30,"rooms":29},
{"id":31,"name":"Standard","price":"$80.66","about":"Consectetur adipiscing elit","adults":2,"image":"image1.jpg","chidrens":31,"rooms":23},
{"id":32,"name":"Suite","price":"$13.76","about":"Lorem ipsum dolor sit amet","adults":6,"image":"image4.jpg","chidrens":32,"rooms":11},
{"id":33,"name":"Standard","price":"$20.81","about":"Lorem ipsum dolor sit amet","adults":0,"image":"image4.jpg","chidrens":33,"rooms":7},
{"id":34,"name":"Executive","price":"$72.76","about":"Ut labore et dolore magna aliqua","adults":21,"image":"image4.jpg","chidrens":34,"rooms":19},
{"id":35,"name":"Presidential","price":"$58.74","about":"Ut enim ad minim veniam","adults":30,"image":"image2.jpg","chidrens":35,"rooms":13},
{"id":36,"name":"Executive","price":"$57.94","about":"Ut labore et dolore magna aliqua","adults":25,"image":"image1.jpg","chidrens":36,"rooms":3},
{"id":37,"name":"Executive","price":"$46.02","about":"Sed do eiusmod tempor incididunt","adults":19,"image":"image1.jpg","chidrens":37,"rooms":12},
{"id":38,"name":"Standard","price":"$82.83","about":"Ut enim ad minim veniam","adults":11,"image":"image5.jpg","chidrens":38,"rooms":17},
{"id":39,"name":"Deluxe","price":"$17.47","about":"Ut labore et dolore magna aliqua","adults":5,"image":"image4.jpg","chidrens":39,"rooms":14},
{"id":40,"name":"Deluxe","price":"$55.06","about":"Sed do eiusmod tempor incididunt","adults":30,"image":"image4.jpg","chidrens":40,"rooms":15},
{"id":41,"name":"Presidential","price":"$52.65","about":"Sed do eiusmod tempor incididunt","adults":9,"image":"image1.jpg","chidrens":41,"rooms":22},
{"id":42,"name":"Deluxe","price":"$48.45","about":"Ut labore et dolore magna aliqua","adults":6,"image":"image3.jpg","chidrens":42,"rooms":10},
{"id":43,"name":"Presidential","price":"$12.10","about":"Lorem ipsum dolor sit amet","adults":20,"image":"image2.jpg","chidrens":43,"rooms":12},
{"id":44,"name":"Standard","price":"$7.81","about":"Ut enim ad minim veniam","adults":7,"image":"image3.jpg","chidrens":44,"rooms":6},
{"id":45,"name":"Presidential","price":"$59.60","about":"Ut enim ad minim veniam","adults":23,"image":"image2.jpg","chidrens":45,"rooms":26},
{"id":46,"name":"Deluxe","price":"$40.64","about":"Consectetur adipiscing elit","adults":5,"image":"image2.jpg","chidrens":46,"rooms":10},
{"id":47,"name":"Suite","price":"$1.50","about":"Lorem ipsum dolor sit amet","adults":24,"image":"image1.jpg","chidrens":47,"rooms":6},
{"id":48,"name":"Standard","price":"$73.21","about":"Consectetur adipiscing elit","adults":11,"image":"image1.jpg","chidrens":48,"rooms":30},
{"id":49,"name":"Executive","price":"$37.30","about":"Ut labore et dolore magna aliqua","adults":23,"image":"image3.jpg","chidrens":49,"rooms":28},
{"id":50,"name":"Executive","price":"$3.40","about":"Sed do eiusmod tempor incididunt","adults":17,"image":"image2.jpg","chidrens":50,"rooms":8}]